dbc_gptcli-0.23.2.dist-info/licenses/LICENSE
gptcli/__init__.py
gptcli/_version.py
gptcli/constants.py
gptcli/main.py
gptcli/src/__init__.py
gptcli/src/cli.py
gptcli/src/install.py
gptcli/src/common/__init__.py
gptcli/src/common/api.py
gptcli/src/common/constants.py
gptcli/src/common/decorators.py
gptcli/src/common/ingest.py
gptcli/src/common/message.py
gptcli/src/common/storage.py
gptcli/src/common/validators.py
gptcli/src/modes/__init__.py
gptcli/src/modes/chat.py
gptcli/src/modes/optical_character_recognition.py
gptcli/src/modes/single_exchange.py
gptcli/tests/__init__.py
gptcli/tests/test_ingest.py
gptcli/tests/test_message.py
gptcli/tests/common/__init__.py
gptcli/tests/common/api.py
gptcli/tests/common/test_constants.py
gptcli/tests/common/test_storage.py
gptcli/tests/common/test_validators.py
gptcli/tests/modes/__init__.py
gptcli/tests/modes/test_chat.py
gptcli/tests/modes/test_optical_character_recognition.py
gptcli/tests/modes/test_single_exchange.py
dbc_gptcli-0.23.2.dist-info/METADATA
dbc_gptcli-0.23.2.dist-info/WHEEL
dbc_gptcli-0.23.2.dist-info/entry_points.txt
dbc_gptcli-0.23.2.dist-info/top_level.txt
dbc_gptcli-0.23.2.dist-info/RECORD
