Metadata-Version: 2.4
Name: dbc-gptcli
Version: 0.23.2
Summary: A CLI tool for accessing OpenAI and Mistral AI LLMs
Author-email: Damian Vonapartis <damianosvon@gmail.com>
License-Expression: GPL-3.0
Project-URL: Repository, https://github.com/deathbychocolate/gptcli
Keywords: openai,mistral,llm,gpt,cli,gptcli,terminal,chat,api
Classifier: Intended Audience :: Developers
Classifier: Operating System :: POSIX
Classifier: Operating System :: POSIX :: Linux
Classifier: Operating System :: Unix
Classifier: Operating System :: MacOS :: MacOS X
Classifier: Programming Language :: Python
Classifier: Programming Language :: Python :: 3
Classifier: Programming Language :: Python :: 3 :: Only
Classifier: Programming Language :: Python :: 3.11
Classifier: Programming Language :: Python :: 3.12
Classifier: Programming Language :: Python :: 3.13
Classifier: Programming Language :: Python :: 3.14
Requires-Python: >=3.11
License-File: LICENSE
Requires-Dist: filetype<2.0.0,>=1.2.0
Requires-Dist: requests<3.0.0,>=2.32.4
Requires-Dist: prompt-toolkit<4.0.0,>=3.0.51
Requires-Dist: pypdf<6.0.0,>=5.7.0
Requires-Dist: tiktoken<1.0.0,>=0.11.0
Requires-Dist: mistral-common<2.0.0,>=1.8.4
Requires-Dist: validators<1.0.0,>=0.35.0
Dynamic: license-file
